{
  "variants": {
    "facing=east,shape=straight": { "model": "tfcr:block/leafroof/straight" },
    "facing=south,shape=straight": { "model": "tfcr:block/leafroof/straight", "y": 90 },
    "facing=west,shape=straight": { "model": "tfcr:block/leafroof/straight", "y": 180 },
    "facing=north,shape=straight": { "model": "tfcr:block/leafroof/straight", "y": 270 },

    "facing=east,shape=outer_right": { "model": "tfcr:block/leafroof/outer_corner", "y": 90 },
    "facing=south,shape=outer_right": { "model": "tfcr:block/leafroof/outer_corner", "y": 180 },
    "facing=west,shape=outer_right": { "model": "tfcr:block/leafroof/outer_corner", "y": 270 },
    "facing=north,shape=outer_right": { "model": "tfcr:block/leafroof/outer_corner", "y": 0 },

    "facing=east,shape=outer_left": { "model": "tfcr:block/leafroof/outer_corner", "y": 0 },
    "facing=south,shape=outer_left": { "model": "tfcr:block/leafroof/outer_corner", "y": 90 },
    "facing=west,shape=outer_left": { "model": "tfcr:block/leafroof/outer_corner", "y": 180 },
    "facing=north,shape=outer_left": { "model": "tfcr:block/leafroof/outer_corner", "y": 270 },

    "facing=east,shape=inner_right": { "model": "tfcr:block/leafroof/inner_corner", "y": 90 },
    "facing=south,shape=inner_right": { "model": "tfcr:block/leafroof/inner_corner", "y": 180 },
    "facing=west,shape=inner_right": { "model": "tfcr:block/leafroof/inner_corner", "y": 270 },
    "facing=north,shape=inner_right": { "model": "tfcr:block/leafroof/inner_corner", "y": 0 },

    "facing=east,shape=inner_left": { "model": "tfcr:block/leafroof/inner_corner", "y": 0 },
    "facing=south,shape=inner_left": { "model": "tfcr:block/leafroof/inner_corner", "y": 90 },
    "facing=west,shape=inner_left": { "model": "tfcr:block/leafroof/inner_corner", "y": 180 },
    "facing=north,shape=inner_left": { "model": "tfcr:block/leafroof/inner_corner", "y": 270 },

    "facing=east,shape=center": { "model": "tfcr:block/leafroof/center", "y": 0 },
    "facing=south,shape=center": { "model": "tfcr:block/leafroof/center", "y": 90 },
    "facing=west,shape=center": { "model": "tfcr:block/leafroof/center", "y": 180 },
    "facing=north,shape=center": { "model": "tfcr:block/leafroof/center", "y": 270 }
  }
}